{"id":"entities/brightsmile-dental","title":"BrightSmile Dental","type":"entities","html":"<blockquote>\n<p>Stub. Cosmetic-dentistry client (<code>brightsmiledental.com</code>) on the <a href=\"#\" class=\"mind-link\" data-node-id=\"projects/rankett\">Rankett</a> platform — possibly a real client, possibly demo data. Contact Lisa Wong (<code>lisa@brightsmiledental.com</code>), status ACTIVE with bi-weekly auto-analyses (2/1, 2/15, 3/1 2026), \"PENDING MSA\" badge (<a href=\"#\" class=\"mind-link\" data-node-id=\"summaries/2026-03-04-screenshot-2026-03-04-at-3-03-56-pm-628ba1f0\">2026 03 04 screenshot 2026 03 04 at 3 03 56 pm 628ba1f0</a>, <a href=\"#\" class=\"mind-link\" data-node-id=\"summaries/2026-03-04-screenshot-2026-03-04-at-3-04-20-pm-f3150906\">2026 03 04 screenshot 2026 03 04 at 3 04 20 pm f3150906</a>).</p>\n</blockquote>\n","related":[{"id":"summaries/2026-03-04-screenshot-2026-03-04-at-3-04-20-pm-f3150906","label":"BrightSmile Dental — client info Lisa Wong, cosmetic dentistry"},{"id":"summaries/2026-03-04-screenshot-2026-03-04-at-3-03-56-pm-628ba1f0","label":"BrightSmile Dental client — analysis history, pending MSA"},{"id":"projects/rankett","label":"Rankett"}]}
