{"id":"summaries/2025-12-19-call-with-nonas","title":"Call with Nonas","type":"summaries","html":"<p>December 2025 Apple Note from <a href=\"#\" class=\"mind-link\" data-node-id=\"entities/yahir-gonzalez\">Yahir</a> containing only a <code>com.apple.m4a-audio</code> placeholder — a phone-call recording with \"Nonas\" (likely grandmother) that didn't re-import as audio. Body has no text. Companion to the audio-orphan pattern in <a href=\"#\" class=\"mind-link\" data-node-id=\"summaries/2026-01-07-call-with-emily-stevens\">2026 01 07 call with emily stevens</a>.</p>\n<p><a href=\"#\" class=\"mind-link\" data-node-id=\"entities/yahir-gonzalez\">yahir gonzalez</a> · <a href=\"#\" class=\"mind-link\" data-node-id=\"entities/austin-tx\">austin tx</a> · <a href=\"#\" class=\"mind-link\" data-node-id=\"summaries/2026-01-07-call-with-emily-stevens\">2026 01 07 call with emily stevens</a></p>\n","related":[{"id":"entities/austin-tx","label":"Austin, Texas"},{"id":"summaries/2026-01-07-call-with-emily-stevens","label":"Call with Emily Stevens"},{"id":"entities/yahir-gonzalez","label":"Yahir Gonzalez"}]}
