{"id":"entities/calc-251","title":"Calc 251 (OSU calculus)","type":"entities","html":"<blockquote>\n<p>Stub. The spring-2025 calculus course at <a href=\"#\" class=\"mind-link\" data-node-id=\"entities/osu\">OSU</a> whose <a href=\"#\" class=\"mind-link\" data-node-id=\"entities/d2l\">D2L</a> quizzes Yahir screenshotted across May 2025: tangent lines (May 2), log/cosine derivatives (May 13), inverse-trig derivatives (May 16), full derivative-table drill (May 22). Title-numbering inferred from OSU catalog convention; could be MATH 251.</p>\n</blockquote>\n<h2>Related</h2>\n<ul>\n<li><a href=\"#\" class=\"mind-link\" data-node-id=\"entities/osu\">osu</a> · <a href=\"#\" class=\"mind-link\" data-node-id=\"entities/d2l\">d2l</a> · <a href=\"#\" class=\"mind-link\" data-node-id=\"summaries/2025-05-30-todos\">2025 05 30 todos</a></li>\n</ul>\n","related":[{"id":"summaries/2025-05-22-screenshot-2025-05-22-at-8-58-14-am-eabf8dc7","label":"Calc — full derivative table + chain-rule + product/exp drill"},{"id":"summaries/2025-05-16-screenshot-2025-05-16-at-6-58-32-pm-c68901e9","label":"Calc — inverse-trig derivatives quiz"},{"id":"summaries/2025-05-13-screenshot-2025-05-13-at-9-25-47-pm-68789a60","label":"Calc — log-and-cosine derivative quiz"},{"id":"summaries/2025-05-02-screenshot-2025-05-02-at-7-16-11-pm-9a29b40e","label":"Calc — tangent-line problems on trig functions"},{"id":"entities/d2l","label":"D2L (Desire2Learn / Canvas at OSU)"},{"id":"entities/osu","label":"Oregon State University (OSU)"},{"id":"summaries/2025-05-30-todos","label":"Todos — Austin move + Brotein launch + summer 2025 planning"}]}
