{"id":"summaries/2020-01-23-casey","title":"'Casey' — Jan 23 2020 7-second omen","type":"summaries","html":"<p>7-second voice memo titled \"Casey\" — Yahir says <em>\"the universe might be trying to tell you something. First, not Casey. Then you saw Leisha. Then you saw Tr—\"</em> and cuts off. A pattern-noticing micro-omen in the <a href=\"#\" class=\"mind-link\" data-node-id=\"concepts/deja-vu\">deja vu</a> / <a href=\"#\" class=\"mind-link\" data-node-id=\"concepts/heightened-perception-trigger\">heightened perception trigger</a> register, three weeks after the <a href=\"#\" class=\"mind-link\" data-node-id=\"summaries/2020-01-02-voice-memo-0015\">New Year's time capsule</a> where the same Alicia/Leisha/Kai thread surfaces. Worth pairing into a teen-romance synthesis later.</p>\n<p><a href=\"#\" class=\"mind-link\" data-node-id=\"concepts/deja-vu\">deja vu</a> · <a href=\"#\" class=\"mind-link\" data-node-id=\"concepts/heightened-perception-trigger\">heightened perception trigger</a> · <a href=\"#\" class=\"mind-link\" data-node-id=\"concepts/grants-pass-teen-era\">grants pass teen era</a> · <a href=\"#\" class=\"mind-link\" data-node-id=\"concepts/long-distance-relationship-pattern\">long distance relationship pattern</a> · <a href=\"#\" class=\"mind-link\" data-node-id=\"concepts/recording-as-note\">recording as note</a></p>\n","related":[{"id":"concepts/deja-vu","label":"Déjà vu"},{"id":"concepts/grants-pass-teen-era","label":"Grants Pass Teen Era"},{"id":"concepts/heightened-perception-trigger","label":"Heightened-perception trigger"},{"id":"concepts/long-distance-relationship-pattern","label":"Long-Distance Relationship Pattern"},{"id":"concepts/recording-as-note","label":"Recording as Note"},{"id":"summaries/2020-01-02-voice-memo-0015","label":"Time-capsule recording — Jan 2 2020 'recording with my life'"}]}
