{"id":"concepts/premium-rate-sms-fraud","title":"Premium-Rate SMS Fraud","type":"concepts","html":"<blockquote>\n<p>Stub. The dominant monetization for <a href=\"#\" class=\"mind-link\" data-node-id=\"concepts/mobile-malware\">mobile malware</a> in the 2009-2011 era — 24 of 46 samples in the Felt et al. survey. Stealthier than premium-rate calls (no busy line). Defense: require user confirmation per message (which <a href=\"#\" class=\"mind-link\" data-node-id=\"entities/ios\">ios</a> already did). First mentioned in <a href=\"#\" class=\"mind-link\" data-node-id=\"summaries/2025-06-01-screenshot-2025-06-01-at-9-15-26-pm-7f8b8bc5\">2025 06 01 mobile malware credentials sms</a>.</p>\n</blockquote>\n","related":[{"id":"entities/ios","label":"iOS"},{"id":"concepts/mobile-malware","label":"Mobile Malware"},{"id":"summaries/2025-06-01-screenshot-2025-06-01-at-9-15-26-pm-7f8b8bc5","label":"Mobile malware survey — credential theft, premium SMS, 2FA bypass, IMEI defenses"},{"id":"summaries/2025-06-01-screenshot-2025-06-01-at-9-15-20-pm-44f00f66","label":"Mobile malware survey (Felt et al.) — methodology, data set, novelty/amusement, selling user info"}]}
