{"id":"summaries/2025-05-20-screenshot-2025-05-20-at-3-13-49-pm-457b8c06","title":"IDA structs view — procps_scan_t (0x440 bytes) padding-byte fields","type":"summaries","html":"<p><a href=\"#\" class=\"mind-link\" data-node-id=\"entities/ida-pro\">IDA</a> Local Types pane — Yahir's reconstructed <code>procps_scan_t</code> struct (sizeof=0x440) with <code>gid_t</code> typedef'd. Mostly padding bytes pending field discovery — same May 20 <a href=\"#\" class=\"mind-link\" data-node-id=\"entities/busybox\">busybox</a> homework.</p>\n<p><a href=\"#\" class=\"mind-link\" data-node-id=\"entities/ida-pro\">ida pro</a> · <a href=\"#\" class=\"mind-link\" data-node-id=\"entities/busybox\">busybox</a> · <a href=\"#\" class=\"mind-link\" data-node-id=\"concepts/reverse-engineering\">reverse engineering</a> · <a href=\"#\" class=\"mind-link\" data-node-id=\"concepts/cs-coursework\">cs coursework</a></p>\n","related":[{"id":"entities/busybox","label":"BusyBox"},{"id":"concepts/cs-coursework","label":"CS Coursework"},{"id":"entities/ida-pro","label":"IDA Pro"},{"id":"concepts/reverse-engineering","label":"Reverse Engineering"}]}
