{"id":"summaries/2025-10-20-screenshot-2025-10-20-at-11-10-20-am-da0d3de8","title":"Instagram — Abrazo de Oso (Buenos Aires nonprofit) profile","type":"summaries","html":"<p>Instagram profile of abrazo de oso — a Buenos Aires (CABA) nonprofit \"acompañamos a personas en situación de vulnerabilidad\" (8,872 followers, 48 posts) that Yahir bookmarked, possibly while researching mission-driven orgs in Argentina.</p>\n<p>abrazo de oso · buenos aires · argentina · nonprofits yahir tracks</p>\n","related":[{"id":"unresolved/abrazo-de-oso","label":"abrazo de oso"},{"id":"unresolved/argentina","label":"argentina"},{"id":"unresolved/buenos-aires","label":"buenos aires"},{"id":"unresolved/nonprofits-yahir-tracks","label":"nonprofits yahir tracks"}]}
