{"id":"entities/stripe","title":"Stripe","type":"entities","html":"<blockquote>\n<p>Stub. Billing infrastructure used by <a href=\"#\" class=\"mind-link\" data-node-id=\"projects/rankett\">Rankett</a> for the agency partner program (per-seat $998/mo subscriptions, per-client activation-anniversary billing). First mentioned across the Jan 2026 Rankett docs (<a href=\"#\" class=\"mind-link\" data-node-id=\"summaries/2026-01-05-rankett-infrastructure\">2026 01 05 rankett infrastructure</a>, <a href=\"#\" class=\"mind-link\" data-node-id=\"summaries/2026-02-03-emily-spanish-assignment\">the demo flow embedded in Emily's Spanish doc</a>).</p>\n</blockquote>\n","related":[{"id":"summaries/2026-01-05-rankett-infrastructure","label":"2026 01 05 Rankett Infrastructure"},{"id":"entities/alipay","label":"AliPay"},{"id":"summaries/2026-02-03-emily-spanish-assignment","label":"Emily Spanish assignment — deforestation/wildfires essay + Rankett demo flow stitched in"},{"id":"projects/rankett","label":"Rankett"},{"id":"summaries/2026-02-08-screenshot-2026-02-08-at-2-14-10-am-149037ed","label":"Stripe setup guide — recurring payments"},{"id":"summaries/2026-02-20-screenshot-2026-02-20-at-2-24-53-pm-b27de694","label":"Vrtl Pirates Partner Plan — $299/mo billing"}]}
