{"id":"concepts/sichuan-food","title":"Sichuan Food","type":"concepts","html":"<h1>Sichuan Food</h1>\n<blockquote>\n<p>Stub. First mentioned in <a href=\"#\" class=\"mind-link\" data-node-id=\"summaries/2024-09-25-things-to-do-in-chengdu\">2024 09 25 things to do in chengdu</a>.</p>\n</blockquote>\n<p>The cuisine of Sichuan province (<a href=\"#\" class=\"mind-link\" data-node-id=\"entities/chengdu\">chengdu</a> is the capital). Famous for mala (numbing-spicy), Sichuan peppercorn, hotpot, mapo tofu, twice-cooked pork, and the frog dishes Yahir tried (97 CNY for the \"5th frog meal\" stood out).</p>\n<h2>Related</h2>\n<ul>\n<li><a href=\"#\" class=\"mind-link\" data-node-id=\"entities/chengdu\">chengdu</a></li>\n<li><a href=\"#\" class=\"mind-link\" data-node-id=\"concepts/china-chapter\">china chapter</a></li>\n</ul>\n","related":[{"id":"entities/chengdu","label":"Chengdu"},{"id":"concepts/china-chapter","label":"China Chapter"},{"id":"summaries/2024-10-02-ChongDu","label":"ChongDu — Chongqing + Chengdu mid-Shanghai-semester trip"},{"id":"index","label":"Index"},{"id":"synthesis/the-china-chapter-as-comparative-anthropology","label":"The China Chapter As Comparative Anthropology"},{"id":"summaries/2024-09-25-things-to-do-in-chengdu","label":"Things to do in Chengdu — itinerary + meal log"},{"id":"entities/xi-an","label":"Xi'an"},{"id":"summaries/2024-11-07-xi-an","label":"Xi'an — 3-day itinerary + food hit-list"}]}
