{"id":"summaries/2023-07-23-names-and-kid-conditions","title":"NAMES — kid-name shortlist + birth-condition wishlist (2023)","type":"summaries","html":"<h1>NAMES — kid-name shortlist + birth-condition wishlist (2023)</h1>\n<blockquote>\n<p>Source: 2023-07-23 Apple Note (modified through 2026-03 — actively edited for 2.5 years). <strong>Future-kid name brainstorm</strong> + a list of weird birth-conditions Yahir wants for his kids.</p>\n</blockquote>\n<h2>TL;DR</h2>\n<ul>\n<li><strong>Active 2.5-year doc</strong> — created 2023-07-23, last modified 2026-03-15, meaning Yahir keeps revisiting his kid-name list. <strong>Real intent</strong>, not a one-time brainstorm.</li>\n<li><strong>Girl candidates</strong>: Jrei, Jordana, Georgina, Luci, Sailor, Gina, Jana, Zora, Avari.</li>\n<li><strong>Boy candidates</strong>: Giovanni, Jovani, Dorian, Napoleone, Marvin, Gilbert, Jon___.</li>\n<li><strong>Birth-condition wishlist</strong> (the weirder layer): <em>\"chose own name, born in random ass island/country, born on a boat, godfather is a random celeb or stranger, name have the ü.\"</em> Yahir wants his kids to start with origin-mythos.</li>\n<li><strong>Pattern</strong>: Yahir's voice extends to <em>engineering origin stories for descendants</em>. Same forward-bending energy as <a href=\"#\" class=\"mind-link\" data-node-id=\"concepts/mom-house-by-the-river\">mom house by the river</a> but generationally projected.</li>\n</ul>\n<h2>Connections</h2>\n<ul>\n<li><a href=\"#\" class=\"mind-link\" data-node-id=\"concepts/mom-house-by-the-river\">mom house by the river</a></li>\n<li><a href=\"#\" class=\"mind-link\" data-node-id=\"entities/yahir-family\">yahir family</a></li>\n<li><a href=\"#\" class=\"mind-link\" data-node-id=\"concepts/lineage-as-fate\">lineage as fate</a></li>\n<li><a href=\"#\" class=\"mind-link\" data-node-id=\"concepts/non-negotiables-for-traveling\">non negotiables for traveling</a> — name-have-the-ü is travel-romanticism leaking into family</li>\n<li><a href=\"#\" class=\"mind-link\" data-node-id=\"summaries/2022-09-04-never-been-in-love-vietnamese-fucked\">2022 09 04 never been in love vietnamese fucked</a> — earlier baseline (no love yet)</li>\n</ul>\n","related":[{"id":"concepts/lineage-as-fate","label":"Lineage as Fate"},{"id":"concepts/mom-house-by-the-river","label":"Mom-house-by-the-river"},{"id":"summaries/2022-09-04-never-been-in-love-vietnamese-fucked","label":"Never been in love + Vietnamese family fuck-over premonition (2022)"},{"id":"concepts/non-negotiables-for-traveling","label":"Non-Negotiables for Traveling"},{"id":"entities/yahir-family","label":"Yahir's Family"}]}
