{"id":"summaries/2025-07-22-screenshot-2025-07-22-at-12-00-29-am-a23b3b1e","title":"Two-character screenshot — 'M kcal'","type":"summaries","html":"<p><code>M</code> + <code>kcal</code> — likely a <a href=\"#\" class=\"mind-link\" data-node-id=\"projects/brotein\">Brotein</a> UI label fragment (the M is probably a Male-icon glyph next to the calorie unit). Sibling of the 12:00:22 \"Close\" capture.</p>\n<p><a href=\"#\" class=\"mind-link\" data-node-id=\"projects/brotein\">brotein</a> · <a href=\"#\" class=\"mind-link\" data-node-id=\"entities/swiftui\">swiftui</a> · <a href=\"#\" class=\"mind-link\" data-node-id=\"entities/bromenu\">bromenu</a></p>\n","related":[{"id":"entities/bromenu","label":"BroMenu"},{"id":"projects/brotein","label":"Brotein"},{"id":"entities/swiftui","label":"SwiftUI"}]}
